.pre-commit-config.yaml
.python-version
.travis.yml
LICENSE
MANIFEST.in
README.rst
flake8_illegal_import.py
makefile
setup.cfg
setup.py
test_flake8_illegal_import.py
flake8_illegal_import.egg-info/PKG-INFO
flake8_illegal_import.egg-info/SOURCES.txt
flake8_illegal_import.egg-info/dependency_links.txt
flake8_illegal_import.egg-info/entry_points.txt
flake8_illegal_import.egg-info/not-zip-safe
flake8_illegal_import.egg-info/requires.txt
flake8_illegal_import.egg-info/top_level.txt
tests/files/sample.py