Metadata-Version: 1.2
Name: flake8-illegal-import
Version: 0.1.0
Summary: illegal import detector, plugin for flake8
Home-page: https://github.com/bagerard/flake8-illegal-import
Maintainer: Bastien Gérard
Maintainer-email: bastien.gerard@gmail.com
License: MIT License
Keywords: flake8 import reject
Platform: UNKNOWN
Classifier: Development Status :: 3 - Alpha
Classifier: Environment :: Console
Classifier: Intended Audience :: Developers
Classifier: License :: OSI Approved :: MIT License
Classifier: Operating System :: OS Independent
Classifier: Programming Language :: Python
Classifier: Programming Language :: Python :: 2.7
Classifier: Programming Language :: Python :: 3
Classifier: Topic :: Software Development :: Libraries :: Python Modules
Classifier: Topic :: Software Development :: Quality Assurance
